{
  "id": "2138320",
  "name": "pa d",
  "font_family": "iconfont",
  "css_prefix_text": "icon",
  "description": "",
  "glyphs": [
    {
      "icon_id": "929015",
      "name": "bluetooth",
      "font_class": "bluetooth",
      "unicode": "e658",
      "unicode_decimal": 58968
    },
    {
      "icon_id": "1261197",
      "name": "bluetooth-b",
      "font_class": "bluetooth-b",
      "unicode": "e64d",
      "unicode_decimal": 58957
    },
    {
      "icon_id": "3262684",
      "name": "化学 实验",
      "font_class": "huaxueshiyan",
      "unicode": "e60b",
      "unicode_decimal": 58891
    },
    {
      "icon_id": "5252501",
      "name": "损坏",
      "font_class": "sunhuai",
      "unicode": "e627",
      "unicode_decimal": 58919
    },
    {
      "icon_id": "5482973",
      "name": "化学用品",
      "font_class": "huaxueyongpin",
      "unicode": "e690",
      "unicode_decimal": 59024
    },
    {
      "icon_id": "10268440",
      "name": "病理",
      "font_class": "bingli",
      "unicode": "e66d",
      "unicode_decimal": 58989
    },
    {
      "icon_id": "15884662",
      "name": "感染科",
      "font_class": "ganranke",
      "unicode": "e603",
      "unicode_decimal": 58883
    },
    {
      "icon_id": "16328327",
      "name": "药",
      "font_class": "yao",
      "unicode": "e66a",
      "unicode_decimal": 58986
    },
    {
      "icon_id": "7448293",
      "name": "back",
      "font_class": "back",
      "unicode": "e669",
      "unicode_decimal": 58985
    },
    {
      "icon_id": "1969467",
      "name": "切换",
      "font_class": "qiehuan",
      "unicode": "e621",
      "unicode_decimal": 58913
    },
    {
      "icon_id": "5327580",
      "name": "加号",
      "font_class": "jiahao",
      "unicode": "e71e",
      "unicode_decimal": 59166
    },
    {
      "icon_id": "5327581",
      "name": "加号2",
      "font_class": "jiahao1",
      "unicode": "e71f",
      "unicode_decimal": 59167
    },
    {
      "icon_id": "5327587",
      "name": "加号3",
      "font_class": "jiahao2",
      "unicode": "e720",
      "unicode_decimal": 59168
    },
    {
      "icon_id": "5327589",
      "name": "加载",
      "font_class": "jiazai1",
      "unicode": "e721",
      "unicode_decimal": 59169
    },
    {
      "icon_id": "5327591",
      "name": "驾照",
      "font_class": "jiazhao",
      "unicode": "e722",
      "unicode_decimal": 59170
    },
    {
      "icon_id": "5327593",
      "name": "减号",
      "font_class": "jianhao",
      "unicode": "e723",
      "unicode_decimal": 59171
    },
    {
      "icon_id": "5327597",
      "name": "减号2",
      "font_class": "jianhao1",
      "unicode": "e724",
      "unicode_decimal": 59172
    },
    {
      "icon_id": "5327601",
      "name": "减号3",
      "font_class": "jianhao2",
      "unicode": "e725",
      "unicode_decimal": 59173
    },
    {
      "icon_id": "5327603",
      "name": "剪切板",
      "font_class": "jianqieban",
      "unicode": "e726",
      "unicode_decimal": 59174
    },
    {
      "icon_id": "5327605",
      "name": "建筑",
      "font_class": "jianzhu",
      "unicode": "e727",
      "unicode_decimal": 59175
    },
    {
      "icon_id": "5327608",
      "name": "键盘",
      "font_class": "jianpan",
      "unicode": "e728",
      "unicode_decimal": 59176
    },
    {
      "icon_id": "5327610",
      "name": "箭头-上",
      "font_class": "jiantou-shang",
      "unicode": "e729",
      "unicode_decimal": 59177
    },
    {
      "icon_id": "5327615",
      "name": "箭头-上下",
      "font_class": "jiantou-shangxia",
      "unicode": "e72a",
      "unicode_decimal": 59178
    },
    {
      "icon_id": "5327616",
      "name": "箭头-拖动",
      "font_class": "jiantou-tuodong",
      "unicode": "e72b",
      "unicode_decimal": 59179
    },
    {
      "icon_id": "5327617",
      "name": "箭头-下",
      "font_class": "jiantou-xia",
      "unicode": "e72c",
      "unicode_decimal": 59180
    },
    {
      "icon_id": "5327619",
      "name": "箭头-右",
      "font_class": "jiantou-you",
      "unicode": "e72d",
      "unicode_decimal": 59181
    },
    {
      "icon_id": "5327620",
      "name": "箭头-左",
      "font_class": "jiantou-zuo",
      "unicode": "e72e",
      "unicode_decimal": 59182
    },
    {
      "icon_id": "5327623",
      "name": "箭头-左右",
      "font_class": "jiantou-zuoyou",
      "unicode": "e72f",
      "unicode_decimal": 59183
    },
    {
      "icon_id": "5327624",
      "name": "奖杯",
      "font_class": "jiangbei",
      "unicode": "e730",
      "unicode_decimal": 59184
    },
    {
      "icon_id": "5327625",
      "name": "降级",
      "font_class": "jiangji",
      "unicode": "e731",
      "unicode_decimal": 59185
    },
    {
      "icon_id": "5327626",
      "name": "交换",
      "font_class": "jiaohuan",
      "unicode": "e732",
      "unicode_decimal": 59186
    },
    {
      "icon_id": "5327627",
      "name": "街景",
      "font_class": "jiejing",
      "unicode": "e733",
      "unicode_decimal": 59187
    },
    {
      "icon_id": "5327630",
      "name": "解锁",
      "font_class": "jiesuo",
      "unicode": "e734",
      "unicode_decimal": 59188
    },
    {
      "icon_id": "5327632",
      "name": "解锁2",
      "font_class": "jiesuo1",
      "unicode": "e735",
      "unicode_decimal": 59189
    },
    {
      "icon_id": "5327633",
      "name": "禁止",
      "font_class": "jinzhi",
      "unicode": "e736",
      "unicode_decimal": 59190
    },
    {
      "icon_id": "5327634",
      "name": "井号",
      "font_class": "jinghao",
      "unicode": "e737",
      "unicode_decimal": 59191
    },
    {
      "icon_id": "5327635",
      "name": "救护车",
      "font_class": "jiuhuche",
      "unicode": "e738",
      "unicode_decimal": 59192
    },
    {
      "icon_id": "5327636",
      "name": "救生圈",
      "font_class": "jiushengquan",
      "unicode": "e739",
      "unicode_decimal": 59193
    },
    {
      "icon_id": "5327637",
      "name": "咖啡",
      "font_class": "kafei",
      "unicode": "e73a",
      "unicode_decimal": 59194
    },
    {
      "icon_id": "5327639",
      "name": "卡车",
      "font_class": "qiache",
      "unicode": "e73b",
      "unicode_decimal": 59195
    },
    {
      "icon_id": "5327640",
      "name": "快进",
      "font_class": "kuaijin",
      "unicode": "e73c",
      "unicode_decimal": 59196
    },
    {
      "icon_id": "5327642",
      "name": "快退",
      "font_class": "kuaitui",
      "unicode": "e73d",
      "unicode_decimal": 59197
    },
    {
      "icon_id": "5327644",
      "name": "扩音器",
      "font_class": "kuoyinqi",
      "unicode": "e73e",
      "unicode_decimal": 59198
    },
    {
      "icon_id": "5327647",
      "name": "垃圾桶2",
      "font_class": "lajitong",
      "unicode": "e740",
      "unicode_decimal": 59200
    },
    {
      "icon_id": "5327653",
      "name": "蓝牙",
      "font_class": "lanya",
      "unicode": "e741",
      "unicode_decimal": 59201
    },
    {
      "icon_id": "5327654",
      "name": "礼物",
      "font_class": "liwu",
      "unicode": "e742",
      "unicode_decimal": 59202
    },
    {
      "icon_id": "5327655",
      "name": "历史记录",
      "font_class": "lishijilu",
      "unicode": "e743",
      "unicode_decimal": 59203
    },
    {
      "icon_id": "5327657",
      "name": "立方体",
      "font_class": "lifangti",
      "unicode": "e744",
      "unicode_decimal": 59204
    },
    {
      "icon_id": "5327658",
      "name": "立方体组",
      "font_class": "lifangtizu",
      "unicode": "e745",
      "unicode_decimal": 59205
    },
    {
      "icon_id": "5327659",
      "name": "链接",
      "font_class": "lianjie",
      "unicode": "e746",
      "unicode_decimal": 59206
    },
    {
      "icon_id": "5329911",
      "name": "链接-断开",
      "font_class": "lianjie-duankai",
      "unicode": "e747",
      "unicode_decimal": 59207
    },
    {
      "icon_id": "5329937",
      "name": "列",
      "font_class": "lie",
      "unicode": "e748",
      "unicode_decimal": 59208
    },
    {
      "icon_id": "5329938",
      "name": "列表",
      "font_class": "liebiao",
      "unicode": "e749",
      "unicode_decimal": 59209
    },
    {
      "icon_id": "5329944",
      "name": "列表2",
      "font_class": "liebiao1",
      "unicode": "e74a",
      "unicode_decimal": 59210
    },
    {
      "icon_id": "5329946",
      "name": "列表3",
      "font_class": "liebiao2",
      "unicode": "e74b",
      "unicode_decimal": 59211
    },
    {
      "icon_id": "5329948",
      "name": "铃声",
      "font_class": "lingsheng",
      "unicode": "e74c",
      "unicode_decimal": 59212
    },
    {
      "icon_id": "5329949",
      "name": "铃声-静音",
      "font_class": "lingsheng-jingyin",
      "unicode": "e74d",
      "unicode_decimal": 59213
    },
    {
      "icon_id": "5329953",
      "name": "轮船",
      "font_class": "lunchuan",
      "unicode": "e74e",
      "unicode_decimal": 59214
    },
    {
      "icon_id": "5329955",
      "name": "螺栓",
      "font_class": "luoshuan",
      "unicode": "e74f",
      "unicode_decimal": 59215
    },
    {
      "icon_id": "5329957",
      "name": "麦克风",
      "font_class": "maikefeng",
      "unicode": "e750",
      "unicode_decimal": 59216
    },
    {
      "icon_id": "5329958",
      "name": "麦克风-静音",
      "font_class": "maikefeng-jingyin",
      "unicode": "e751",
      "unicode_decimal": 59217
    },
    {
      "icon_id": "5329979",
      "name": "地图锚",
      "font_class": "ditumao",
      "unicode": "e752",
      "unicode_decimal": 59218
    },
    {
      "icon_id": "5330012",
      "name": "名片",
      "font_class": "mingpian",
      "unicode": "e753",
      "unicode_decimal": 59219
    },
    {
      "icon_id": "5330016",
      "name": "魔术棒",
      "font_class": "moshubang",
      "unicode": "e755",
      "unicode_decimal": 59221
    },
    {
      "icon_id": "5330019",
      "name": "男士",
      "font_class": "nanshi",
      "unicode": "e756",
      "unicode_decimal": 59222
    },
    {
      "icon_id": "5330020",
      "name": "男性",
      "font_class": "nanxing",
      "unicode": "e757",
      "unicode_decimal": 59223
    },
    {
      "icon_id": "5330024",
      "name": "匿名用户",
      "font_class": "nimingyonghu",
      "unicode": "e758",
      "unicode_decimal": 59224
    },
    {
      "icon_id": "5330026",
      "name": "女士",
      "font_class": "nvshi",
      "unicode": "e759",
      "unicode_decimal": 59225
    },
    {
      "icon_id": "5330030",
      "name": "女性",
      "font_class": "nvxing",
      "unicode": "e75a",
      "unicode_decimal": 59226
    },
    {
      "icon_id": "4678340",
      "name": "close",
      "font_class": "close",
      "unicode": "e71b",
      "unicode_decimal": 59163
    },
    {
      "icon_id": "5330032",
      "name": "排序",
      "font_class": "paixu",
      "unicode": "e75b",
      "unicode_decimal": 59227
    },
    {
      "icon_id": "5321591",
      "name": "Excel",
      "font_class": "Excel",
      "unicode": "e637",
      "unicode_decimal": 58935
    },
    {
      "icon_id": "5330036",
      "name": "排序-降序",
      "font_class": "paixu-jiangxu",
      "unicode": "e75c",
      "unicode_decimal": 59228
    },
    {
      "icon_id": "5321593",
      "name": "image",
      "font_class": "image",
      "unicode": "e638",
      "unicode_decimal": 58936
    },
    {
      "icon_id": "5330057",
      "name": "排序-升序",
      "font_class": "paixu-shengxu",
      "unicode": "e75d",
      "unicode_decimal": 59229
    },
    {
      "icon_id": "5321594",
      "name": "pdf",
      "font_class": "pdf",
      "unicode": "e639",
      "unicode_decimal": 58937
    },
    {
      "icon_id": "5330119",
      "name": "排序-数量降序",
      "font_class": "paixu-shuliangjiangxu",
      "unicode": "e75e",
      "unicode_decimal": 59230
    },
    {
      "icon_id": "5321600",
      "name": "ppt",
      "font_class": "ppt",
      "unicode": "e63a",
      "unicode_decimal": 58938
    },
    {
      "icon_id": "5330123",
      "name": "排序-数量升序",
      "font_class": "paixu-shuliangshengxu",
      "unicode": "e75f",
      "unicode_decimal": 59231
    },
    {
      "icon_id": "5321601",
      "name": "txt",
      "font_class": "txt",
      "unicode": "e63b",
      "unicode_decimal": 58939
    },
    {
      "icon_id": "5330126",
      "name": "票",
      "font_class": "piao",
      "unicode": "e760",
      "unicode_decimal": 59232
    },
    {
      "icon_id": "5321634",
      "name": "word",
      "font_class": "word",
      "unicode": "e63c",
      "unicode_decimal": 58940
    },
    {
      "icon_id": "5330127",
      "name": "平板电脑",
      "font_class": "pingbandiannao",
      "unicode": "e761",
      "unicode_decimal": 59233
    },
    {
      "icon_id": "5321636",
      "name": "zip",
      "font_class": "zip",
      "unicode": "e63d",
      "unicode_decimal": 58941
    },
    {
      "icon_id": "5330144",
      "name": "评论",
      "font_class": "pinglun",
      "unicode": "e763",
      "unicode_decimal": 59235
    },
    {
      "icon_id": "5321637",
      "name": "扳手",
      "font_class": "banshou",
      "unicode": "e63e",
      "unicode_decimal": 58942
    },
    {
      "icon_id": "5330146",
      "name": "评论2",
      "font_class": "pinglun1",
      "unicode": "e764",
      "unicode_decimal": 59236
    },
    {
      "icon_id": "5321639",
      "name": "保存",
      "font_class": "baocun",
      "unicode": "e63f",
      "unicode_decimal": 58943
    },
    {
      "icon_id": "5330148",
      "name": "评论组",
      "font_class": "pinglunzu",
      "unicode": "e765",
      "unicode_decimal": 59237
    },
    {
      "icon_id": "5321642",
      "name": "报警警报预警",
      "font_class": "baojing",
      "unicode": "e640",
      "unicode_decimal": 58944
    },
    {
      "icon_id": "5330159",
      "name": "评论组2",
      "font_class": "pinglunzu1",
      "unicode": "e766",
      "unicode_decimal": 59238
    },
    {
      "icon_id": "5321647",
      "name": "比对碰撞",
      "font_class": "biduipengzhuang",
      "unicode": "e641",
      "unicode_decimal": 58945
    },
    {
      "icon_id": "5330160",
      "name": "旗帜",
      "font_class": "qizhi",
      "unicode": "e767",
      "unicode_decimal": 59239
    },
    {
      "icon_id": "5321650",
      "name": "车辆碰撞",
      "font_class": "cheliangpengzhuang",
      "unicode": "e642",
      "unicode_decimal": 58946
    },
    {
      "icon_id": "5330172",
      "name": "铅笔",
      "font_class": "qianbi",
      "unicode": "e768",
      "unicode_decimal": 59240
    },
    {
      "icon_id": "5321651",
      "name": "大楼3",
      "font_class": "dalou3",
      "unicode": "e643",
      "unicode_decimal": 58947
    },
    {
      "icon_id": "5330181",
      "name": "前进",
      "font_class": "qianjin",
      "unicode": "e76a",
      "unicode_decimal": 59242
    },
    {
      "icon_id": "5321662",
      "name": "大楼1",
      "font_class": "dalou1",
      "unicode": "e644",
      "unicode_decimal": 58948
    },
    {
      "icon_id": "5330224",
      "name": "前进2",
      "font_class": "qianjin1",
      "unicode": "e76b",
      "unicode_decimal": 59243
    },
    {
      "icon_id": "5321666",
      "name": "大楼2",
      "font_class": "dalou2",
      "unicode": "e645",
      "unicode_decimal": 58949
    },
    {
      "icon_id": "5330236",
      "name": "全屏",
      "font_class": "quanping",
      "unicode": "e76c",
      "unicode_decimal": 59244
    },
    {
      "icon_id": "5321692",
      "name": "大脑",
      "font_class": "danao",
      "unicode": "e646",
      "unicode_decimal": 58950
    },
    {
      "icon_id": "5330237",
      "name": "人民币",
      "font_class": "renminbi",
      "unicode": "e76d",
      "unicode_decimal": 59245
    },
    {
      "icon_id": "5321694",
      "name": "档案1",
      "font_class": "dangan1",
      "unicode": "e647",
      "unicode_decimal": 58951
    },
    {
      "icon_id": "5330238",
      "name": "人字形-上",
      "font_class": "renzixing-shang",
      "unicode": "e76e",
      "unicode_decimal": 59246
    },
    {
      "icon_id": "5321704",
      "name": "档案",
      "font_class": "dangan",
      "unicode": "e648",
      "unicode_decimal": 58952
    },
    {
      "icon_id": "5330245",
      "name": "人字形-下",
      "font_class": "renzixing-xia",
      "unicode": "e76f",
      "unicode_decimal": 59247
    },
    {
      "icon_id": "5321707",
      "name": "地图尺子",
      "font_class": "dituchizi",
      "unicode": "e649",
      "unicode_decimal": 58953
    },
    {
      "icon_id": "5330260",
      "name": "人字形-右",
      "font_class": "renzixing-you",
      "unicode": "e770",
      "unicode_decimal": 59248
    },
    {
      "icon_id": "5321708",
      "name": "地图加油站",
      "font_class": "ditujiayouzhan",
      "unicode": "e64a",
      "unicode_decimal": 58954
    },
    {
      "icon_id": "5330261",
      "name": "人字形-左",
      "font_class": "renzixing-zuo",
      "unicode": "e771",
      "unicode_decimal": 59249
    },
    {
      "icon_id": "5321710",
      "name": "地图连线1",
      "font_class": "ditulianxian",
      "unicode": "e64b",
      "unicode_decimal": 58955
    },
    {
      "icon_id": "5330263",
      "name": "任务",
      "font_class": "renwu",
      "unicode": "e772",
      "unicode_decimal": 59250
    },
    {
      "icon_id": "5321712",
      "name": "地图连线转移",
      "font_class": "ditulianxianzhuanyi",
      "unicode": "e64c",
      "unicode_decimal": 58956
    },
    {
      "icon_id": "5330265",
      "name": "日历",
      "font_class": "rili",
      "unicode": "e773",
      "unicode_decimal": 59251
    },
    {
      "icon_id": "5321715",
      "name": "地图石油",
      "font_class": "ditushiyou",
      "unicode": "e64e",
      "unicode_decimal": 58958
    },
    {
      "icon_id": "5330288",
      "name": "日历2",
      "font_class": "rili1",
      "unicode": "e774",
      "unicode_decimal": 59252
    },
    {
      "icon_id": "5321716",
      "name": "地图-手指",
      "font_class": "ditu-shouzhi",
      "unicode": "e64f",
      "unicode_decimal": 58959
    },
    {
      "icon_id": "5330293",
      "name": "上传",
      "font_class": "shangchuan",
      "unicode": "e775",
      "unicode_decimal": 59253
    },
    {
      "icon_id": "5321724",
      "name": "地图组织架构",
      "font_class": "dituzuzhijiagou",
      "unicode": "e650",
      "unicode_decimal": 58960
    },
    {
      "icon_id": "5330295",
      "name": "烧瓶",
      "font_class": "shaoping",
      "unicode": "e776",
      "unicode_decimal": 59254
    },
    {
      "icon_id": "5321726",
      "name": "地图组织站点",
      "font_class": "dituzuzhizhandian",
      "unicode": "e651",
      "unicode_decimal": 58961
    },
    {
      "icon_id": "5330329",
      "name": "摄像机",
      "font_class": "shexiangji",
      "unicode": "e777",
      "unicode_decimal": 59255
    },
    {
      "icon_id": "5321731",
      "name": "电池电量",
      "font_class": "dianchidianliang",
      "unicode": "e652",
      "unicode_decimal": 58962
    },
    {
      "icon_id": "5330330",
      "name": "升级",
      "font_class": "shengji",
      "unicode": "e778",
      "unicode_decimal": 59256
    },
    {
      "icon_id": "5321738",
      "name": "电话固话",
      "font_class": "dianhuaguhua",
      "unicode": "e653",
      "unicode_decimal": 58963
    },
    {
      "icon_id": "5330332",
      "name": "时钟",
      "font_class": "shizhong",
      "unicode": "e779",
      "unicode_decimal": 59257
    },
    {
      "icon_id": "5321740",
      "name": "电脑",
      "font_class": "diannao",
      "unicode": "e654",
      "unicode_decimal": 58964
    },
    {
      "icon_id": "5330393",
      "name": "收件箱",
      "font_class": "shoujianxiang",
      "unicode": "e77a",
      "unicode_decimal": 59258
    },
    {
      "icon_id": "5321741",
      "name": "定位",
      "font_class": "dingwei",
      "unicode": "e655",
      "unicode_decimal": 58965
    },
    {
      "icon_id": "5330396",
      "name": "收起",
      "font_class": "shouqi",
      "unicode": "e77b",
      "unicode_decimal": 59259
    },
    {
      "icon_id": "5321742",
      "name": "毒品危险",
      "font_class": "dupinweixian",
      "unicode": "e656",
      "unicode_decimal": 58966
    },
    {
      "icon_id": "5330397",
      "name": "手提包",
      "font_class": "shoutibao",
      "unicode": "e77c",
      "unicode_decimal": 59260
    },
    {
      "icon_id": "5321744",
      "name": "分屏对比",
      "font_class": "fenpingduibi",
      "unicode": "e657",
      "unicode_decimal": 58967
    },
    {
      "icon_id": "5330399",
      "name": "手提箱",
      "font_class": "shoutixiang",
      "unicode": "e77d",
      "unicode_decimal": 59261
    },
    {
      "icon_id": "5321758",
      "name": "分享",
      "font_class": "fenxiang",
      "unicode": "e659",
      "unicode_decimal": 58969
    },
    {
      "icon_id": "5330400",
      "name": "首页",
      "font_class": "shouye",
      "unicode": "e77e",
      "unicode_decimal": 59262
    },
    {
      "icon_id": "5321762",
      "name": "分享转发",
      "font_class": "fenxiangzhuanfa",
      "unicode": "e65a",
      "unicode_decimal": 58970
    },
    {
      "icon_id": "5330402",
      "name": "书籍",
      "font_class": "shuji",
      "unicode": "e77f",
      "unicode_decimal": 59263
    },
    {
      "icon_id": "5321764",
      "name": "服务器",
      "font_class": "fuwuqi",
      "unicode": "e65b",
      "unicode_decimal": 58971
    },
    {
      "icon_id": "5330403",
      "name": "书签",
      "font_class": "shuqian",
      "unicode": "e780",
      "unicode_decimal": 59264
    },
    {
      "icon_id": "5321771",
      "name": "服务器主机",
      "font_class": "fuwuqizhuji",
      "unicode": "e65c",
      "unicode_decimal": 58972
    },
    {
      "icon_id": "5330405",
      "name": "鼠标指针",
      "font_class": "shubiaozhizhen",
      "unicode": "e781",
      "unicode_decimal": 59265
    },
    {
      "icon_id": "5321774",
      "name": "附件",
      "font_class": "fujian",
      "unicode": "e65d",
      "unicode_decimal": 58973
    },
    {
      "icon_id": "5330406",
      "name": "数据库",
      "font_class": "shujuku",
      "unicode": "e782",
      "unicode_decimal": 59266
    },
    {
      "icon_id": "5321775",
      "name": "复制比对",
      "font_class": "fuzhibidui",
      "unicode": "e65e",
      "unicode_decimal": 58974
    },
    {
      "icon_id": "5330407",
      "name": "刷新",
      "font_class": "shuaxin",
      "unicode": "e783",
      "unicode_decimal": 59267
    },
    {
      "icon_id": "5321776",
      "name": "公安盾牌",
      "font_class": "gongandunpai",
      "unicode": "e65f",
      "unicode_decimal": 58975
    },
    {
      "icon_id": "5330409",
      "name": "双角符-上",
      "font_class": "shuangjiaofu-shang",
      "unicode": "e784",
      "unicode_decimal": 59268
    },
    {
      "icon_id": "5321778",
      "name": "管理流转协作",
      "font_class": "guanliliuzhuanxiezuo",
      "unicode": "e660",
      "unicode_decimal": 58976
    },
    {
      "icon_id": "5330411",
      "name": "双角符-下",
      "font_class": "shuangjiaofu-xia",
      "unicode": "e785",
      "unicode_decimal": 59269
    },
    {
      "icon_id": "5321787",
      "name": "轨迹",
      "font_class": "guiji",
      "unicode": "e661",
      "unicode_decimal": 58977
    },
    {
      "icon_id": "5330413",
      "name": "双角符-右",
      "font_class": "shuangjiaofu-you",
      "unicode": "e786",
      "unicode_decimal": 59270
    },
    {
      "icon_id": "5321789",
      "name": "轨迹1",
      "font_class": "guiji1",
      "unicode": "e662",
      "unicode_decimal": 58978
    },
    {
      "icon_id": "5330415",
      "name": "双角符-左",
      "font_class": "shuangjiaofu-zuo",
      "unicode": "e787",
      "unicode_decimal": 59271
    },
    {
      "icon_id": "5321790",
      "name": "红绿灯违章",
      "font_class": "honglvdengweizhang",
      "unicode": "e663",
      "unicode_decimal": 58979
    },
    {
      "icon_id": "5330418",
      "name": "随机",
      "font_class": "suiji",
      "unicode": "e788",
      "unicode_decimal": 59272
    },
    {
      "icon_id": "5321791",
      "name": "画板主题",
      "font_class": "huabanzhuti",
      "unicode": "e664",
      "unicode_decimal": 58980
    },
    {
      "icon_id": "5330431",
      "name": "缩进-减",
      "font_class": "suojin-jian",
      "unicode": "e789",
      "unicode_decimal": 59273
    },
    {
      "icon_id": "5321792",
      "name": "货币钱袋资金",
      "font_class": "huobiqiandaizijin",
      "unicode": "e665",
      "unicode_decimal": 58981
    },
    {
      "icon_id": "5330435",
      "name": "锁定",
      "font_class": "suoding",
      "unicode": "e78a",
      "unicode_decimal": 59274
    },
    {
      "icon_id": "5321794",
      "name": "基站信号",
      "font_class": "jizhanxinhao",
      "unicode": "e666",
      "unicode_decimal": 58982
    },
    {
      "icon_id": "5330436",
      "name": "叹号",
      "font_class": "tanhao",
      "unicode": "e78b",
      "unicode_decimal": 59275
    },
    {
      "icon_id": "5321796",
      "name": "加载",
      "font_class": "jiazai",
      "unicode": "e667",
      "unicode_decimal": 58983
    },
    {
      "icon_id": "5330437",
      "name": "叹号2",
      "font_class": "tanhao1",
      "unicode": "e78c",
      "unicode_decimal": 59276
    },
    {
      "icon_id": "5321798",
      "name": "监控控制管理监管",
      "font_class": "jiankongkongzhiguanlijianguan",
      "unicode": "e668",
      "unicode_decimal": 58984
    },
    {
      "icon_id": "5330439",
      "name": "填色",
      "font_class": "tianse",
      "unicode": "e78d",
      "unicode_decimal": 59277
    },
    {
      "icon_id": "5321806",
      "name": "大楼建筑",
      "font_class": "dalou4",
      "unicode": "e66b",
      "unicode_decimal": 58987
    },
    {
      "icon_id": "5330440",
      "name": "条形码",
      "font_class": "tiaoxingma",
      "unicode": "e78e",
      "unicode_decimal": 59278
    },
    {
      "icon_id": "5321857",
      "name": "警察半身",
      "font_class": "jingchabanshen",
      "unicode": "e66e",
      "unicode_decimal": 58990
    },
    {
      "icon_id": "5330443",
      "name": "调整",
      "font_class": "tiaozheng",
      "unicode": "e78f",
      "unicode_decimal": 59279
    },
    {
      "icon_id": "5321868",
      "name": "卡口摄像头",
      "font_class": "qiakoushexiangtou",
      "unicode": "e670",
      "unicode_decimal": 58992
    },
    {
      "icon_id": "5330444",
      "name": "听诊器",
      "font_class": "tingzhenqi",
      "unicode": "e790",
      "unicode_decimal": 59280
    },
    {
      "icon_id": "5321875",
      "name": "快递包裹",
      "font_class": "kuaidibaoguo",
      "unicode": "e671",
      "unicode_decimal": 58993
    },
    {
      "icon_id": "5330448",
      "name": "停止",
      "font_class": "tingzhi",
      "unicode": "e791",
      "unicode_decimal": 59281
    },
    {
      "icon_id": "5321877",
      "name": "枪支",
      "font_class": "qiangzhi",
      "unicode": "e672",
      "unicode_decimal": 58994
    },
    {
      "icon_id": "5330449",
      "name": "停止2",
      "font_class": "tingzhi1",
      "unicode": "e792",
      "unicode_decimal": 59282
    },
    {
      "icon_id": "5321879",
      "name": "认证徽章",
      "font_class": "renzhenghuizhang",
      "unicode": "e673",
      "unicode_decimal": 58995
    },
    {
      "icon_id": "5330451",
      "name": "通讯录",
      "font_class": "tongxunlu",
      "unicode": "e793",
      "unicode_decimal": 59283
    },
    {
      "icon_id": "5321881",
      "name": "入室盗窃",
      "font_class": "rushidaoqie",
      "unicode": "e675",
      "unicode_decimal": 58997
    },
    {
      "icon_id": "5330452",
      "name": "图表",
      "font_class": "tubiao",
      "unicode": "e794",
      "unicode_decimal": 59284
    },
    {
      "icon_id": "5321886",
      "name": "社交qq",
      "font_class": "shejiaoqq",
      "unicode": "e676",
      "unicode_decimal": 58998
    },
    {
      "icon_id": "5330453",
      "name": "图钉",
      "font_class": "tuding",
      "unicode": "e795",
      "unicode_decimal": 59285
    },
    {
      "icon_id": "5321887",
      "name": "社交钉钉",
      "font_class": "shejiaodingding",
      "unicode": "e677",
      "unicode_decimal": 58999
    },
    {
      "icon_id": "5330455",
      "name": "图片",
      "font_class": "tupian",
      "unicode": "e796",
      "unicode_decimal": 59286
    },
    {
      "icon_id": "5321888",
      "name": "社交飞信",
      "font_class": "shejiaofeixin",
      "unicode": "e678",
      "unicode_decimal": 59000
    },
    {
      "icon_id": "5330461",
      "name": "退出",
      "font_class": "tuichu",
      "unicode": "e797",
      "unicode_decimal": 59287
    },
    {
      "icon_id": "5321889",
      "name": "社交米聊",
      "font_class": "shejiaomiliao",
      "unicode": "e679",
      "unicode_decimal": 59001
    },
    {
      "icon_id": "5330501",
      "name": "微芯片",
      "font_class": "weixinpian",
      "unicode": "e79a",
      "unicode_decimal": 59290
    },
    {
      "icon_id": "5321891",
      "name": "社交陌陌图标",
      "font_class": "shejiaomomotubiao",
      "unicode": "e67a",
      "unicode_decimal": 59002
    },
    {
      "icon_id": "5330502",
      "name": "文件",
      "font_class": "wenjian",
      "unicode": "e79b",
      "unicode_decimal": 59291
    },
    {
      "icon_id": "5321892",
      "name": "社交微博",
      "font_class": "shejiaoweibo",
      "unicode": "e67b",
      "unicode_decimal": 59003
    },
    {
      "icon_id": "5330504",
      "name": "文件夹",
      "font_class": "wenjianjia",
      "unicode": "e79c",
      "unicode_decimal": 59292
    },
    {
      "icon_id": "5321947",
      "name": "卡口监控摄像头",
      "font_class": "qiakoujiankongshexiangtou",
      "unicode": "e67e",
      "unicode_decimal": 59006
    },
    {
      "icon_id": "5330506",
      "name": "文件夹-打开",
      "font_class": "wenjianjia-dakai",
      "unicode": "e79d",
      "unicode_decimal": 59293
    },
    {
      "icon_id": "5321958",
      "name": "卡口视频摄像头",
      "font_class": "qiakoujiankongshexiangtou1",
      "unicode": "e67f",
      "unicode_decimal": 59007
    },
    {
      "icon_id": "5330508",
      "name": "文件-文本",
      "font_class": "wenjian-wenben",
      "unicode": "e79e",
      "unicode_decimal": 59294
    },
    {
      "icon_id": "5321970",
      "name": "审批",
      "font_class": "shenpi",
      "unicode": "e680",
      "unicode_decimal": 59008
    },
    {
      "icon_id": "5330509",
      "name": "文件组",
      "font_class": "wenjianzu",
      "unicode": "e79f",
      "unicode_decimal": 59295
    },
    {
      "icon_id": "5321971",
      "name": "时间",
      "font_class": "shijian",
      "unicode": "e681",
      "unicode_decimal": 59009
    },
    {
      "icon_id": "5330515",
      "name": "问号",
      "font_class": "wenhao",
      "unicode": "e7a1",
      "unicode_decimal": 59297
    },
    {
      "icon_id": "5321972",
      "name": "视频",
      "font_class": "shipin",
      "unicode": "e682",
      "unicode_decimal": 59010
    },
    {
      "icon_id": "5330622",
      "name": "下载",
      "font_class": "xiazai",
      "unicode": "e7a3",
      "unicode_decimal": 59299
    },
    {
      "icon_id": "5321992",
      "name": "AVI视频文件",
      "font_class": "AVIshipinwenjian-copy",
      "unicode": "e685",
      "unicode_decimal": 59013
    },
    {
      "icon_id": "5330623",
      "name": "线图",
      "font_class": "xiantu",
      "unicode": "e7a4",
      "unicode_decimal": 59300
    },
    {
      "icon_id": "5322071",
      "name": "台式机",
      "font_class": "taishiji",
      "unicode": "e688",
      "unicode_decimal": 59016
    },
    {
      "icon_id": "5330624",
      "name": "相机",
      "font_class": "xiangji",
      "unicode": "e7a5",
      "unicode_decimal": 59301
    },
    {
      "icon_id": "5322077",
      "name": "天平公平研判",
      "font_class": "tianpinggongpingyanpan",
      "unicode": "e689",
      "unicode_decimal": 59017
    },
    {
      "icon_id": "5330625",
      "name": "相机-旧式",
      "font_class": "xiangji-jiushi",
      "unicode": "e7a6",
      "unicode_decimal": 59302
    },
    {
      "icon_id": "5322079",
      "name": "团队",
      "font_class": "tuandui",
      "unicode": "e68a",
      "unicode_decimal": 59018
    },
    {
      "icon_id": "5330626",
      "name": "项目列表",
      "font_class": "xiangmuliebiao",
      "unicode": "e7a7",
      "unicode_decimal": 59303
    },
    {
      "icon_id": "5322083",
      "name": "消息-成功",
      "font_class": "xiaoxi-chenggong",
      "unicode": "e68c",
      "unicode_decimal": 59020
    },
    {
      "icon_id": "5330643",
      "name": "小汽车",
      "font_class": "xiaoqiche",
      "unicode": "e7a8",
      "unicode_decimal": 59304
    },
    {
      "icon_id": "5322085",
      "name": "消息-警告",
      "font_class": "xiaoxi-jinggao",
      "unicode": "e68d",
      "unicode_decimal": 59021
    },
    {
      "icon_id": "5330644",
      "name": "心形",
      "font_class": "xinxing",
      "unicode": "e7a9",
      "unicode_decimal": 59305
    },
    {
      "icon_id": "5322089",
      "name": "消息-信息",
      "font_class": "xiaoxi-xinxi",
      "unicode": "e68f",
      "unicode_decimal": 59023
    },
    {
      "icon_id": "5330645",
      "name": "信封",
      "font_class": "xinfeng",
      "unicode": "e7aa",
      "unicode_decimal": 59306
    },
    {
      "icon_id": "5322137",
      "name": "消息-失败",
      "font_class": "xiaoxi-shibai",
      "unicode": "e691",
      "unicode_decimal": 59025
    },
    {
      "icon_id": "5330646",
      "name": "信封2",
      "font_class": "xinfeng1",
      "unicode": "e7ab",
      "unicode_decimal": 59307
    },
    {
      "icon_id": "5322139",
      "name": "协同",
      "font_class": "xietong",
      "unicode": "e692",
      "unicode_decimal": 59026
    },
    {
      "icon_id": "5330648",
      "name": "信号",
      "font_class": "xinhao",
      "unicode": "e7ac",
      "unicode_decimal": 59308
    },
    {
      "icon_id": "5322149",
      "name": "新闻",
      "font_class": "xinwen",
      "unicode": "e695",
      "unicode_decimal": 59029
    },
    {
      "icon_id": "5330653",
      "name": "信息",
      "font_class": "xinxi",
      "unicode": "e7ad",
      "unicode_decimal": 59309
    },
    {
      "icon_id": "5322159",
      "name": "新闻报纸",
      "font_class": "xinwenbaozhi",
      "unicode": "e696",
      "unicode_decimal": 59030
    },
    {
      "icon_id": "5330656",
      "name": "信用卡2",
      "font_class": "xinyongqia",
      "unicode": "e7af",
      "unicode_decimal": 59311
    },
    {
      "icon_id": "5322169",
      "name": "研判锤子",
      "font_class": "yanpanchuizi",
      "unicode": "e698",
      "unicode_decimal": 59032
    },
    {
      "icon_id": "5330657",
      "name": "星号",
      "font_class": "xinghao",
      "unicode": "e7b0",
      "unicode_decimal": 59312
    },
    {
      "icon_id": "5322171",
      "name": "用户-男",
      "font_class": "yonghu-nan",
      "unicode": "e69a",
      "unicode_decimal": 59034
    },
    {
      "icon_id": "5330658",
      "name": "星形",
      "font_class": "xingxing",
      "unicode": "e7b1",
      "unicode_decimal": 59313
    },
    {
      "icon_id": "5322174",
      "name": "用户-女",
      "font_class": "yonghu-nv",
      "unicode": "e69b",
      "unicode_decimal": 59035
    },
    {
      "icon_id": "5330664",
      "name": "星形半颗",
      "font_class": "xingxingbanke",
      "unicode": "e7b3",
      "unicode_decimal": 59315
    },
    {
      "icon_id": "5322175",
      "name": "圆形布局",
      "font_class": "yuanxingbuju",
      "unicode": "e69c",
      "unicode_decimal": 59036
    },
    {
      "icon_id": "5330665",
      "name": "眼睛",
      "font_class": "yanjing",
      "unicode": "e7b4",
      "unicode_decimal": 59316
    },
    {
      "icon_id": "5322176",
      "name": "云搜系统",
      "font_class": "yunsouxitong",
      "unicode": "e69d",
      "unicode_decimal": 59037
    },
    {
      "icon_id": "5330666",
      "name": "眼睛-斜线",
      "font_class": "yanjing-xiexian",
      "unicode": "e7b5",
      "unicode_decimal": 59317
    },
    {
      "icon_id": "5322181",
      "name": "粘贴",
      "font_class": "niantie",
      "unicode": "e69e",
      "unicode_decimal": 59038
    },
    {
      "icon_id": "5330670",
      "name": "移动设备手机",
      "font_class": "yidongshebei",
      "unicode": "e7b7",
      "unicode_decimal": 59319
    },
    {
      "icon_id": "5322182",
      "name": "站点网站互联网ie",
      "font_class": "zhandianwangzhanhulianwangie",
      "unicode": "e69f",
      "unicode_decimal": 59039
    },
    {
      "icon_id": "5330671",
      "name": "音乐",
      "font_class": "yinle",
      "unicode": "e7b8",
      "unicode_decimal": 59320
    },
    {
      "icon_id": "5322184",
      "name": "账单",
      "font_class": "zhangdan",
      "unicode": "e6a0",
      "unicode_decimal": 59040
    },
    {
      "icon_id": "5330673",
      "name": "音量-低",
      "font_class": "yinliang-di",
      "unicode": "e7b9",
      "unicode_decimal": 59321
    },
    {
      "icon_id": "5322187",
      "name": "支付-京东",
      "font_class": "zhifu-jingdong",
      "unicode": "e6a2",
      "unicode_decimal": 59042
    },
    {
      "icon_id": "5330675",
      "name": "音量-高",
      "font_class": "yinliang-gao",
      "unicode": "e7ba",
      "unicode_decimal": 59322
    },
    {
      "icon_id": "5322190",
      "name": "支付-淘宝",
      "font_class": "zhifu-taobao",
      "unicode": "e6a3",
      "unicode_decimal": 59043
    },
    {
      "icon_id": "5330684",
      "name": "音量-关",
      "font_class": "yinliang-guan",
      "unicode": "e7bb",
      "unicode_decimal": 59323
    },
    {
      "icon_id": "5322192",
      "name": "支付-银联",
      "font_class": "zhifu-yinlian",
      "unicode": "e6a4",
      "unicode_decimal": 59044
    },
    {
      "icon_id": "5330691",
      "name": "音量控制",
      "font_class": "yinliangkongzhi",
      "unicode": "e7bc",
      "unicode_decimal": 59324
    },
    {
      "icon_id": "5322194",
      "name": "支付-支付宝",
      "font_class": "zhifu-zhifubao",
      "unicode": "e6a5",
      "unicode_decimal": 59045
    },
    {
      "icon_id": "5330692",
      "name": "用户",
      "font_class": "yonghu",
      "unicode": "e7bd",
      "unicode_decimal": 59325
    },
    {
      "icon_id": "5322195",
      "name": "指纹",
      "font_class": "zhiwen",
      "unicode": "e6a6",
      "unicode_decimal": 59046
    },
    {
      "icon_id": "5330699",
      "name": "用户-医生",
      "font_class": "yonghu-yisheng",
      "unicode": "e7bf",
      "unicode_decimal": 59327
    },
    {
      "icon_id": "5322196",
      "name": "组织合作协作",
      "font_class": "zuzhihezuoxiezuo",
      "unicode": "e6a7",
      "unicode_decimal": 59047
    },
    {
      "icon_id": "5330702",
      "name": "用户组",
      "font_class": "yonghuzu",
      "unicode": "e7c0",
      "unicode_decimal": 59328
    },
    {
      "icon_id": "5322198",
      "name": "组织群体",
      "font_class": "zuzhiqunti",
      "unicode": "e6a8",
      "unicode_decimal": 59048
    },
    {
      "icon_id": "5330767",
      "name": "雨伞",
      "font_class": "yusan",
      "unicode": "e7c1",
      "unicode_decimal": 59329
    },
    {
      "icon_id": "5325609",
      "name": "婴儿-儿童",
      "font_class": "yinger-ertong",
      "unicode": "e6a9",
      "unicode_decimal": 59049
    },
    {
      "icon_id": "5330820",
      "name": "圆点",
      "font_class": "yuandian",
      "unicode": "e7c2",
      "unicode_decimal": 59330
    },
    {
      "icon_id": "5325622",
      "name": "小偷-逃犯",
      "font_class": "xiaotou-taofan",
      "unicode": "e6aa",
      "unicode_decimal": 59050
    },
    {
      "icon_id": "5330821",
      "name": "圆形",
      "font_class": "yuanxing",
      "unicode": "e7c3",
      "unicode_decimal": 59331
    },
    {
      "icon_id": "5325623",
      "name": "尸体",
      "font_class": "shiti",
      "unicode": "e6ab",
      "unicode_decimal": 59051
    },
    {
      "icon_id": "5330822",
      "name": "圆形2",
      "font_class": "yuanxing1",
      "unicode": "e7c4",
      "unicode_decimal": 59332
    },
    {
      "icon_id": "5325624",
      "name": "串并",
      "font_class": "chuanbing",
      "unicode": "e6ac",
      "unicode_decimal": 59052
    },
    {
      "icon_id": "5330824",
      "name": "云端",
      "font_class": "yunduan",
      "unicode": "e7c5",
      "unicode_decimal": 59333
    },
    {
      "icon_id": "5325625",
      "name": "关系",
      "font_class": "guanxi",
      "unicode": "e6ad",
      "unicode_decimal": 59053
    },
    {
      "icon_id": "5330825",
      "name": "云端链接",
      "font_class": "yunduanlianjie",
      "unicode": "e7c6",
      "unicode_decimal": 59334
    },
    {
      "icon_id": "5325626",
      "name": "手掌",
      "font_class": "shouzhang",
      "unicode": "e6ae",
      "unicode_decimal": 59054
    },
    {
      "icon_id": "5330826",
      "name": "云端上传",
      "font_class": "yunduanshangchuan",
      "unicode": "e7c7",
      "unicode_decimal": 59335
    },
    {
      "icon_id": "5325627",
      "name": "DNA",
      "font_class": "DNA",
      "unicode": "e6af",
      "unicode_decimal": 59055
    },
    {
      "icon_id": "5330831",
      "name": "云端下载",
      "font_class": "yunduanxiazai",
      "unicode": "e7c8",
      "unicode_decimal": 59336
    },
    {
      "icon_id": "5325641",
      "name": "合成作战",
      "font_class": "hechengzuozhan",
      "unicode": "e6b1",
      "unicode_decimal": 59057
    },
    {
      "icon_id": "5330832",
      "name": "暂停",
      "font_class": "zanting",
      "unicode": "e7c9",
      "unicode_decimal": 59337
    },
    {
      "icon_id": "5325643",
      "name": "区域地图",
      "font_class": "quyuditu",
      "unicode": "e6b2",
      "unicode_decimal": 59058
    },
    {
      "icon_id": "5330833",
      "name": "暂停2",
      "font_class": "zanting1",
      "unicode": "e7ca",
      "unicode_decimal": 59338
    },
    {
      "icon_id": "5325646",
      "name": "签字审核",
      "font_class": "qianzishenhe",
      "unicode": "e6b3",
      "unicode_decimal": 59059
    },
    {
      "icon_id": "5330835",
      "name": "展开",
      "font_class": "zhankai",
      "unicode": "e7cb",
      "unicode_decimal": 59339
    },
    {
      "icon_id": "5325647",
      "name": "团伙群体",
      "font_class": "tuanhuoqunti",
      "unicode": "e6b4",
      "unicode_decimal": 59060
    },
    {
      "icon_id": "5330837",
      "name": "战斗机",
      "font_class": "zhandouji",
      "unicode": "e7cc",
      "unicode_decimal": 59340
    },
    {
      "icon_id": "5325649",
      "name": "合作握手",
      "font_class": "hezuowoshou",
      "unicode": "e6b5",
      "unicode_decimal": 59061
    },
    {
      "icon_id": "5330839",
      "name": "站点地图",
      "font_class": "zhandianditu",
      "unicode": "e7cd",
      "unicode_decimal": 59341
    },
    {
      "icon_id": "5325651",
      "name": "案件档案",
      "font_class": "anjiandangan",
      "unicode": "e6b6",
      "unicode_decimal": 59062
    },
    {
      "icon_id": "5330842",
      "name": "长箭头-上",
      "font_class": "changjiantou-shang",
      "unicode": "e7ce",
      "unicode_decimal": 59342
    },
    {
      "icon_id": "5325653",
      "name": "精确搜索查询",
      "font_class": "jingquesousuochaxun",
      "unicode": "e6b7",
      "unicode_decimal": 59063
    },
    {
      "icon_id": "5330844",
      "name": "长箭头-右",
      "font_class": "changjiantou-you",
      "unicode": "e7cf",
      "unicode_decimal": 59343
    },
    {
      "icon_id": "5325654",
      "name": "受害遇害",
      "font_class": "shouhaiyuhai",
      "unicode": "e6b8",
      "unicode_decimal": 59064
    },
    {
      "icon_id": "5330845",
      "name": "长箭头-下",
      "font_class": "changjiantou-xia",
      "unicode": "e7d0",
      "unicode_decimal": 59344
    },
    {
      "icon_id": "5326957",
      "name": "资料身份证档案",
      "font_class": "ziliaoshenfenzhengdangan",
      "unicode": "e6ba",
      "unicode_decimal": 59066
    },
    {
      "icon_id": "5330856",
      "name": "折线图",
      "font_class": "zhexiantu",
      "unicode": "e7d1",
      "unicode_decimal": 59345
    },
    {
      "icon_id": "5327318",
      "name": "rss",
      "font_class": "rss",
      "unicode": "e6bb",
      "unicode_decimal": 59067
    },
    {
      "icon_id": "5330858",
      "name": "重做",
      "font_class": "zhongzuo",
      "unicode": "e7d2",
      "unicode_decimal": 59346
    },
    {
      "icon_id": "5327319",
      "name": "USB",
      "font_class": "USB",
      "unicode": "e6bc",
      "unicode_decimal": 59068
    },
    {
      "icon_id": "5330859",
      "name": "桌面-电脑",
      "font_class": "zhuomian-diannao",
      "unicode": "e7d3",
      "unicode_decimal": 59347
    },
    {
      "icon_id": "5327320",
      "name": "wifi",
      "font_class": "wifi",
      "unicode": "e6bd",
      "unicode_decimal": 59069
    },
    {
      "icon_id": "5330860",
      "name": "转发",
      "font_class": "zhuanfa",
      "unicode": "e7d4",
      "unicode_decimal": 59348
    },
    {
      "icon_id": "5327321",
      "name": "巴士车",
      "font_class": "bashiche",
      "unicode": "e6be",
      "unicode_decimal": 59070
    },
    {
      "icon_id": "5330861",
      "name": "准星",
      "font_class": "zhunxing",
      "unicode": "e7d5",
      "unicode_decimal": 59349
    },
    {
      "icon_id": "5327325",
      "name": "靶心",
      "font_class": "baxin",
      "unicode": "e6bf",
      "unicode_decimal": 59071
    },
    {
      "icon_id": "5330863",
      "name": "最小化",
      "font_class": "zuixiaohua",
      "unicode": "e7d6",
      "unicode_decimal": 59350
    },
    {
      "icon_id": "5327332",
      "name": "百分号",
      "font_class": "baifenhao",
      "unicode": "e6c0",
      "unicode_decimal": 59072
    },
    {
      "icon_id": "5330864",
      "name": "长箭头-左",
      "font_class": "changjiantou-zuo",
      "unicode": "e7d7",
      "unicode_decimal": 59351
    },
    {
      "icon_id": "5327334",
      "name": "扳手",
      "font_class": "banshou1",
      "unicode": "e6c1",
      "unicode_decimal": 59073
    },
    {
      "icon_id": "5330865",
      "name": "纸飞机",
      "font_class": "zhifeiji",
      "unicode": "e7d8",
      "unicode_decimal": 59352
    },
    {
      "icon_id": "5327341",
      "name": "编号列表",
      "font_class": "bianhaoliebiao",
      "unicode": "e6c4",
      "unicode_decimal": 59076
    },
    {
      "icon_id": "5330867",
      "name": "转速表",
      "font_class": "zhuansubiao",
      "unicode": "e7d9",
      "unicode_decimal": 59353
    },
    {
      "icon_id": "5327344",
      "name": "编辑",
      "font_class": "bianji",
      "unicode": "e6c5",
      "unicode_decimal": 59077
    },
    {
      "icon_id": "5330868",
      "name": "指南针",
      "font_class": "zhinanzhen",
      "unicode": "e7da",
      "unicode_decimal": 59354
    },
    {
      "icon_id": "5327345",
      "name": "便签",
      "font_class": "bianqian",
      "unicode": "e6c6",
      "unicode_decimal": 59078
    },
    {
      "icon_id": "5331110",
      "name": "医院",
      "font_class": "yiyuan",
      "unicode": "e7db",
      "unicode_decimal": 59355
    },
    {
      "icon_id": "5327366",
      "name": "标签",
      "font_class": "biaoqian",
      "unicode": "e6c8",
      "unicode_decimal": 59080
    },
    {
      "icon_id": "5331624",
      "name": "笔记本电脑",
      "font_class": "bijibendiannao",
      "unicode": "e7dc",
      "unicode_decimal": 59356
    },
    {
      "icon_id": "5327367",
      "name": "标签组",
      "font_class": "biaoqianzu",
      "unicode": "e6c9",
      "unicode_decimal": 59081
    },
    {
      "icon_id": "5363694",
      "name": "排名",
      "font_class": "paiming",
      "unicode": "e7dd",
      "unicode_decimal": 59357
    },
    {
      "icon_id": "5327369",
      "name": "表格",
      "font_class": "biaoge",
      "unicode": "e6ca",
      "unicode_decimal": 59082
    },
    {
      "icon_id": "5363736",
      "name": "小轿车",
      "font_class": "xiaojiaoche",
      "unicode": "e7de",
      "unicode_decimal": 59358
    },
    {
      "icon_id": "5327371",
      "name": "表格2",
      "font_class": "biaoge1",
      "unicode": "e6cb",
      "unicode_decimal": 59083
    },
    {
      "icon_id": "5363808",
      "name": "自行车",
      "font_class": "zihangche",
      "unicode": "e7df",
      "unicode_decimal": 59359
    },
    {
      "icon_id": "5327373",
      "name": "表格3",
      "font_class": "biaoge2",
      "unicode": "e6cc",
      "unicode_decimal": 59084
    },
    {
      "icon_id": "5363838",
      "name": "摩托车",
      "font_class": "motuoche",
      "unicode": "e7e0",
      "unicode_decimal": 59360
    },
    {
      "icon_id": "5327375",
      "name": "饼图",
      "font_class": "bingtu",
      "unicode": "e6cd",
      "unicode_decimal": 59085
    },
    {
      "icon_id": "5394356",
      "name": "社交微信",
      "font_class": "shejiaoweixin",
      "unicode": "e7e1",
      "unicode_decimal": 59361
    },
    {
      "icon_id": "5327376",
      "name": "播放",
      "font_class": "bofang",
      "unicode": "e6ce",
      "unicode_decimal": 59086
    },
    {
      "icon_id": "5394553",
      "name": "音频",
      "font_class": "yinpin",
      "unicode": "e7e2",
      "unicode_decimal": 59362
    },
    {
      "icon_id": "5327380",
      "name": "播放2",
      "font_class": "bofang1",
      "unicode": "e6cf",
      "unicode_decimal": 59087
    },
    {
      "icon_id": "5394576",
      "name": "手铐",
      "font_class": "shoukao",
      "unicode": "e7e3",
      "unicode_decimal": 59363
    },
    {
      "icon_id": "5327384",
      "name": "博士帽",
      "font_class": "boshimao",
      "unicode": "e6d0",
      "unicode_decimal": 59088
    },
    {
      "icon_id": "5394678",
      "name": "监狱",
      "font_class": "jianyu",
      "unicode": "e7e4",
      "unicode_decimal": 59364
    },
    {
      "icon_id": "5327385",
      "name": "裁剪",
      "font_class": "caijian",
      "unicode": "e6d1",
      "unicode_decimal": 59089
    },
    {
      "icon_id": "5394731",
      "name": "警察",
      "font_class": "jingcha",
      "unicode": "e7e5",
      "unicode_decimal": 59365
    },
    {
      "icon_id": "5327386",
      "name": "餐具",
      "font_class": "canju",
      "unicode": "e6d2",
      "unicode_decimal": 59090
    },
    {
      "icon_id": "5327387",
      "name": "插入符-上",
      "font_class": "charufu-shang",
      "unicode": "e6d3",
      "unicode_decimal": 59091
    },
    {
      "icon_id": "5327388",
      "name": "插入符-下",
      "font_class": "charufu-xia",
      "unicode": "e6d4",
      "unicode_decimal": 59092
    },
    {
      "icon_id": "5327389",
      "name": "插入符-右",
      "font_class": "charufu-you",
      "unicode": "e6d5",
      "unicode_decimal": 59093
    },
    {
      "icon_id": "5327390",
      "name": "插入符-左",
      "font_class": "charufu-zuo",
      "unicode": "e6d6",
      "unicode_decimal": 59094
    },
    {
      "icon_id": "5327391",
      "name": "插头",
      "font_class": "chatou",
      "unicode": "e6d7",
      "unicode_decimal": 59095
    },
    {
      "icon_id": "5327395",
      "name": "查询",
      "font_class": "chaxun",
      "unicode": "e6d8",
      "unicode_decimal": 59096
    },
    {
      "icon_id": "5327398",
      "name": "查询-",
      "font_class": "chaxun-",
      "unicode": "e6d9",
      "unicode_decimal": 59097
    },
    {
      "icon_id": "5327399",
      "name": "查询+",
      "font_class": "chaxun1",
      "unicode": "e6da",
      "unicode_decimal": 59098
    },
    {
      "icon_id": "5327403",
      "name": "差评2",
      "font_class": "chaping",
      "unicode": "e6dc",
      "unicode_decimal": 59100
    },
    {
      "icon_id": "5327404",
      "name": "撤销",
      "font_class": "chexiao",
      "unicode": "e6dd",
      "unicode_decimal": 59101
    },
    {
      "icon_id": "5327405",
      "name": "乘号",
      "font_class": "chenghao",
      "unicode": "e6de",
      "unicode_decimal": 59102
    },
    {
      "icon_id": "5327407",
      "name": "齿轮设置",
      "font_class": "chilunshezhi",
      "unicode": "e6df",
      "unicode_decimal": 59103
    },
    {
      "icon_id": "5327409",
      "name": "齿轮组",
      "font_class": "chilunzu",
      "unicode": "e6e0",
      "unicode_decimal": 59104
    },
    {
      "icon_id": "5327411",
      "name": "臭虫bug",
      "font_class": "chouchongbug",
      "unicode": "e6e1",
      "unicode_decimal": 59105
    },
    {
      "icon_id": "5327412",
      "name": "出租车",
      "font_class": "chuzuche",
      "unicode": "e6e2",
      "unicode_decimal": 59106
    },
    {
      "icon_id": "5327414",
      "name": "传真",
      "font_class": "chuanzhen",
      "unicode": "e6e3",
      "unicode_decimal": 59107
    },
    {
      "icon_id": "5327415",
      "name": "窗口",
      "font_class": "chuangkou",
      "unicode": "e6e4",
      "unicode_decimal": 59108
    },
    {
      "icon_id": "5327417",
      "name": "床",
      "font_class": "chuang",
      "unicode": "e6e5",
      "unicode_decimal": 59109
    },
    {
      "icon_id": "5327418",
      "name": "槌子",
      "font_class": "chuizi",
      "unicode": "e6e6",
      "unicode_decimal": 59110
    },
    {
      "icon_id": "5327419",
      "name": "打印",
      "font_class": "dayin",
      "unicode": "e6e7",
      "unicode_decimal": 59111
    },
    {
      "icon_id": "5327420",
      "name": "大学",
      "font_class": "daxue",
      "unicode": "e6e8",
      "unicode_decimal": 59112
    },
    {
      "icon_id": "5327422",
      "name": "代码-分支",
      "font_class": "daima-fenzhi",
      "unicode": "e6e9",
      "unicode_decimal": 59113
    },
    {
      "icon_id": "5327423",
      "name": "单角符-上",
      "font_class": "danjiaofu-shang",
      "unicode": "e6ea",
      "unicode_decimal": 59114
    },
    {
      "icon_id": "5327428",
      "name": "单角符-下",
      "font_class": "danjiaofu-xia",
      "unicode": "e6eb",
      "unicode_decimal": 59115
    },
    {
      "icon_id": "5327429",
      "name": "单角符-右",
      "font_class": "danjiaofu-you",
      "unicode": "e6ec",
      "unicode_decimal": 59116
    },
    {
      "icon_id": "5327430",
      "name": "单角符-左",
      "font_class": "danjiaofu-zuo",
      "unicode": "e6ed",
      "unicode_decimal": 59117
    },
    {
      "icon_id": "5327431",
      "name": "弹出",
      "font_class": "danchu",
      "unicode": "e6ee",
      "unicode_decimal": 59118
    },
    {
      "icon_id": "5327433",
      "name": "档案",
      "font_class": "dangan2",
      "unicode": "e6ef",
      "unicode_decimal": 59119
    },
    {
      "icon_id": "5327434",
      "name": "登录",
      "font_class": "denglu",
      "unicode": "e6f0",
      "unicode_decimal": 59120
    },
    {
      "icon_id": "5327435",
      "name": "滴管",
      "font_class": "diguan",
      "unicode": "e6f1",
      "unicode_decimal": 59121
    },
    {
      "icon_id": "5327437",
      "name": "地球",
      "font_class": "diqiu",
      "unicode": "e6f2",
      "unicode_decimal": 59122
    },
    {
      "icon_id": "5327438",
      "name": "地铁",
      "font_class": "ditie",
      "unicode": "e6f3",
      "unicode_decimal": 59123
    },
    {
      "icon_id": "5327440",
      "name": "地图",
      "font_class": "ditu",
      "unicode": "e6f4",
      "unicode_decimal": 59124
    },
    {
      "icon_id": "5327459",
      "name": "地图-图钉",
      "font_class": "ditu-tuding",
      "unicode": "e6f5",
      "unicode_decimal": 59125
    },
    {
      "icon_id": "5327460",
      "name": "地图-指示牌",
      "font_class": "ditu-zhishipai",
      "unicode": "e6f6",
      "unicode_decimal": 59126
    },
    {
      "icon_id": "5327464",
      "name": "电灯",
      "font_class": "diandeng",
      "unicode": "e6f8",
      "unicode_decimal": 59128
    },
    {
      "icon_id": "5327466",
      "name": "电话",
      "font_class": "dianhua",
      "unicode": "e6f9",
      "unicode_decimal": 59129
    },
    {
      "icon_id": "5327471",
      "name": "电视-显示器",
      "font_class": "dianshi-xianshiqi",
      "unicode": "e6fa",
      "unicode_decimal": 59130
    },
    {
      "icon_id": "5327475",
      "name": "电影",
      "font_class": "dianying",
      "unicode": "e6fb",
      "unicode_decimal": 59131
    },
    {
      "icon_id": "5327478",
      "name": "电源-关",
      "font_class": "dianyuan-guan",
      "unicode": "e6fc",
      "unicode_decimal": 59132
    },
    {
      "icon_id": "5327479",
      "name": "对号",
      "font_class": "duihao",
      "unicode": "e6fd",
      "unicode_decimal": 59133
    },
    {
      "icon_id": "5327482",
      "name": "盾牌",
      "font_class": "dunpai",
      "unicode": "e6fe",
      "unicode_decimal": 59134
    },
    {
      "icon_id": "5327483",
      "name": "儿童",
      "font_class": "ertong",
      "unicode": "e6ff",
      "unicode_decimal": 59135
    },
    {
      "icon_id": "5327484",
      "name": "二维码",
      "font_class": "erweima",
      "unicode": "e700",
      "unicode_decimal": 59136
    },
    {
      "icon_id": "5327488",
      "name": "方向",
      "font_class": "fangxiang",
      "unicode": "e701",
      "unicode_decimal": 59137
    },
    {
      "icon_id": "5327489",
      "name": "方形",
      "font_class": "fangxing",
      "unicode": "e702",
      "unicode_decimal": 59138
    },
    {
      "icon_id": "5327490",
      "name": "方形2",
      "font_class": "fangxing1",
      "unicode": "e703",
      "unicode_decimal": 59139
    },
    {
      "icon_id": "5327492",
      "name": "飞机",
      "font_class": "feiji",
      "unicode": "e704",
      "unicode_decimal": 59140
    },
    {
      "icon_id": "5327493",
      "name": "分享",
      "font_class": "fenxiang1",
      "unicode": "e705",
      "unicode_decimal": 59141
    },
    {
      "icon_id": "5327495",
      "name": "服务器",
      "font_class": "fuwuqi1",
      "unicode": "e706",
      "unicode_decimal": 59142
    },
    {
      "icon_id": "5327498",
      "name": "复选框",
      "font_class": "fuxuankuang",
      "unicode": "e708",
      "unicode_decimal": 59144
    },
    {
      "icon_id": "5327503",
      "name": "复制",
      "font_class": "fuzhi",
      "unicode": "e709",
      "unicode_decimal": 59145
    },
    {
      "icon_id": "5327505",
      "name": "公路",
      "font_class": "gonglu",
      "unicode": "e70a",
      "unicode_decimal": 59146
    },
    {
      "icon_id": "5327507",
      "name": "公文包",
      "font_class": "gongwenbao",
      "unicode": "e70b",
      "unicode_decimal": 59147
    },
    {
      "icon_id": "5327508",
      "name": "功能",
      "font_class": "gongneng",
      "unicode": "e70c",
      "unicode_decimal": 59148
    },
    {
      "icon_id": "5327509",
      "name": "关闭",
      "font_class": "guanbi",
      "unicode": "e70d",
      "unicode_decimal": 59149
    },
    {
      "icon_id": "5327531",
      "name": "过滤器",
      "font_class": "guolvqi",
      "unicode": "e70e",
      "unicode_decimal": 59150
    },
    {
      "icon_id": "5327534",
      "name": "好评2",
      "font_class": "haoping",
      "unicode": "e711",
      "unicode_decimal": 59153
    },
    {
      "icon_id": "5327535",
      "name": "后退",
      "font_class": "houtui",
      "unicode": "e712",
      "unicode_decimal": 59154
    },
    {
      "icon_id": "5327540",
      "name": "后退2",
      "font_class": "houtui1",
      "unicode": "e713",
      "unicode_decimal": 59155
    },
    {
      "icon_id": "5327544",
      "name": "滑块",
      "font_class": "huakuai",
      "unicode": "e714",
      "unicode_decimal": 59156
    },
    {
      "icon_id": "5327555",
      "name": "徽章",
      "font_class": "huizhang",
      "unicode": "e716",
      "unicode_decimal": 59158
    },
    {
      "icon_id": "5327560",
      "name": "回复",
      "font_class": "huifu",
      "unicode": "e717",
      "unicode_decimal": 59159
    },
    {
      "icon_id": "5327563",
      "name": "回复-全部",
      "font_class": "huifu-quanbu",
      "unicode": "e718",
      "unicode_decimal": 59160
    },
    {
      "icon_id": "5327567",
      "name": "火车",
      "font_class": "huoche",
      "unicode": "e719",
      "unicode_decimal": 59161
    },
    {
      "icon_id": "5327569",
      "name": "火箭",
      "font_class": "huojian",
      "unicode": "e71a",
      "unicode_decimal": 59162
    },
    {
      "icon_id": "5327572",
      "name": "急救箱",
      "font_class": "jijiuxiang",
      "unicode": "e71c",
      "unicode_decimal": 59164
    }
  ]
}
